Metadata-Version: 2.1
Name: primosaOAVC2022
Version: 0.0.2
Summary: Calculate prime numbers
License: UNKNOWN
Platform: UNKNOWN
License-File: LICENSE.txt
